qsogrid.py
qsogrid-0.1.7.dist-info/METADATA
qsogrid-0.1.7.dist-info/WHEEL
qsogrid-0.1.7.dist-info/entry_points.txt
qsogrid-0.1.7.dist-info/licenses/LICENSE
qsogrid-0.1.7.dist-info/RECORD
