Metadata-Version: 2.4
Name: qsogrid
Version: 0.1.7
Summary: QSO into a Maidenhead grid
Project-URL: Homepage, https://github.com/0x9900/qsogrid
Project-URL: Repository, https://github.com/0x9900/qsogrid
Author-email: "Fred C." <github-fred@hidzz.com>
License: BSD 3-Clause License
License-File: LICENSE
Keywords: adif,grid,ham radio,qso
Classifier: Development Status :: 3 - Alpha
Classifier: Intended Audience :: End Users/Desktop
Classifier: Intended Audience :: Telecommunications Industry
Classifier: License :: OSI Approved :: BSD License
Classifier: Programming Language :: Python :: 3.10
Classifier: Programming Language :: Python :: 3.11
Classifier: Programming Language :: Python :: 3.12
Requires-Python: >=3.10
Requires-Dist: adif-io
Requires-Dist: cartopy
Requires-Dist: matplotlib
Provides-Extra: dev
Requires-Dist: build; extra == 'dev'
Requires-Dist: flake8; extra == 'dev'
Requires-Dist: isort; extra == 'dev'
Requires-Dist: mypy; extra == 'dev'
Requires-Dist: pre-commit; extra == 'dev'
Requires-Dist: pylint; extra == 'dev'
